abx_plugin_puppeteer/__init__.py
abx_plugin_puppeteer/binaries.py
abx_plugin_puppeteer/binproviders.py
abx_plugin_puppeteer/config.py
abx_plugin_puppeteer-2024.10.28.dist-info/METADATA
abx_plugin_puppeteer-2024.10.28.dist-info/WHEEL
abx_plugin_puppeteer-2024.10.28.dist-info/entry_points.txt
abx_plugin_puppeteer-2024.10.28.dist-info/RECORD
